pybricks/__init__.py
pybricks/ev3brick.py
pybricks/ev3devices.py
pybricks/parameters.py
pybricks/robotics.py
pybricks/tools.py
lego_mp_skeleton-0.1.9.2019103111.dist-info/LICENSE
lego_mp_skeleton-0.1.9.2019103111.dist-info/METADATA
lego_mp_skeleton-0.1.9.2019103111.dist-info/WHEEL
lego_mp_skeleton-0.1.9.2019103111.dist-info/top_level.txt
lego_mp_skeleton-0.1.9.2019103111.dist-info/RECORD
