Metadata-Version: 2.1
Name: lego-mp-skeleton
Version: 0.1.9.2019103111
Summary: Skeleton for the Lego EV3 MicroPython Port
Home-page: https://github.com/klutzybubbles/lego-micropython-skeleton
Author: Lee Tzilantonis
Author-email: LTzilantonis@gmail.com
License: UNKNOWN
Platform: UNKNOWN
Classifier: Programming Language :: Python :: 3
Classifier: License :: OSI Approved :: MIT License
Classifier: Operating System :: OS Independent
Requires-Dist: enum34
